pretix_all_in_one_accessibility/__init__.py
pretix_all_in_one_accessibility/apps.py
pretix_all_in_one_accessibility/forms.py
pretix_all_in_one_accessibility/urls.py
pretix_all_in_one_accessibility/views.py
pretix_all_in_one_accessibility/static/pretix_all_in_one_accessibility/css/aioa.css
pretix_all_in_one_accessibility/static/pretix_all_in_one_accessibility/icons/1.png
pretix_all_in_one_accessibility/static/pretix_all_in_one_accessibility/icons/10.png
pretix_all_in_one_accessibility/static/pretix_all_in_one_accessibility/icons/11.png
pretix_all_in_one_accessibility/static/pretix_all_in_one_accessibility/icons/12.png
pretix_all_in_one_accessibility/static/pretix_all_in_one_accessibility/icons/13.png
pretix_all_in_one_accessibility/static/pretix_all_in_one_accessibility/icons/14.png
pretix_all_in_one_accessibility/static/pretix_all_in_one_accessibility/icons/15.png
pretix_all_in_one_accessibility/static/pretix_all_in_one_accessibility/icons/16.png
pretix_all_in_one_accessibility/static/pretix_all_in_one_accessibility/icons/17.png
pretix_all_in_one_accessibility/static/pretix_all_in_one_accessibility/icons/18.png
pretix_all_in_one_accessibility/static/pretix_all_in_one_accessibility/icons/19.png
pretix_all_in_one_accessibility/static/pretix_all_in_one_accessibility/icons/2.png
pretix_all_in_one_accessibility/static/pretix_all_in_one_accessibility/icons/20.png
pretix_all_in_one_accessibility/static/pretix_all_in_one_accessibility/icons/21.png
pretix_all_in_one_accessibility/static/pretix_all_in_one_accessibility/icons/22.png
pretix_all_in_one_accessibility/static/pretix_all_in_one_accessibility/icons/23.png
pretix_all_in_one_accessibility/static/pretix_all_in_one_accessibility/icons/24.png
pretix_all_in_one_accessibility/static/pretix_all_in_one_accessibility/icons/25.png
pretix_all_in_one_accessibility/static/pretix_all_in_one_accessibility/icons/26.png
pretix_all_in_one_accessibility/static/pretix_all_in_one_accessibility/icons/27.png
pretix_all_in_one_accessibility-1.0.0.dist-info/licenses/LICENSE
pretix_all_in_one_accessibility-1.0.0.dist-info/METADATA
pretix_all_in_one_accessibility-1.0.0.dist-info/WHEEL
pretix_all_in_one_accessibility-1.0.0.dist-info/entry_points.txt
pretix_all_in_one_accessibility-1.0.0.dist-info/top_level.txt
pretix_all_in_one_accessibility-1.0.0.dist-info/RECORD
