Metadata-Version: 2.4
Name: pretix_all_in_one_accessibility
Version: 1.0.0
Summary: Website accessibility widget for improving WCAG 2.0, 2.1, 2.2 and ADA compliance!
Author: Skynet Technologies USA LLC
Author-email: developer3@skynettechnologies.com
License: MIT
Classifier: Programming Language :: Python :: 3.9
Classifier: Programming Language :: Python :: 3.10
Classifier: Programming Language :: Python :: 3.11
Classifier: Framework :: Django
Classifier: Operating System :: OS Independent
Classifier: License :: OSI Approved :: MIT License
Requires-Python: >=3.9
License-File: LICENSE
Requires-Dist: requests
Dynamic: author
Dynamic: author-email
Dynamic: classifier
Dynamic: description
Dynamic: description-content-type
Dynamic: license
Dynamic: license-file
Dynamic: requires-dist
Dynamic: requires-python
Dynamic: summary
